inputx/__init__.py
inputx/inputx.py
inputx-1.0.3.dist-info/METADATA
inputx-1.0.3.dist-info/WHEEL
inputx-1.0.3.dist-info/RECORD
