Metadata-Version: 2.1
Name: inputx
Version: 1.0.3
Summary: `inputx` is a Python module that provides an advanced input function with various validation options.
License: MIT
Keywords: inputx,inputs,input,advanced input,custom input,enhanced input,filtered input,secure input,password input,terminal input,interactive input,Python input,character filtering,cursor navigation,string validation,keyboard input,real-time input,typing,text input,data validation,terminal applications
Author: KonstantinDigital
Author-email: martyrhartman@yandex.ru
Requires-Python: >=3.6,<4.0
Classifier: License :: OSI Approved :: MIT License
Classifier: Programming Language :: Python :: 3
Classifier: Programming Language :: Python :: 3.6
Classifier: Programming Language :: Python :: 3.7
Classifier: Programming Language :: Python :: 3.8
Classifier: Programming Language :: Python :: 3.9
Classifier: Programming Language :: Python :: 3.10
Classifier: Programming Language :: Python :: 3.11
Classifier: Programming Language :: Python :: 3.12
Classifier: Programming Language :: Python :: 3.13
